classification_tension_for_image/__init__.py
classification_tension_for_image/img_classification.py
classification_tension_for_image/test.py
classification_tension_for_image-0.0.3.dist-info/LICENSE
classification_tension_for_image-0.0.3.dist-info/METADATA
classification_tension_for_image-0.0.3.dist-info/WHEEL
classification_tension_for_image-0.0.3.dist-info/top_level.txt
classification_tension_for_image-0.0.3.dist-info/RECORD
